ssdp/__init__.py
ssdp/__main__.py
ssdp/_version.py
ssdp/aio.py
ssdp/deprecation.py
ssdp/lexers.py
ssdp/messages.py
ssdp/network.py
ssdp-1.3.1.dist-info/entry_points.txt
ssdp-1.3.1.dist-info/licenses/LICENSE
ssdp-1.3.1.dist-info/WHEEL
ssdp-1.3.1.dist-info/METADATA
ssdp-1.3.1.dist-info/RECORD
