Metadata-Version: 2.4
Name: ssdp
Version: 1.3.1
Summary: Python asyncio library for Simple Service Discovery Protocol (SSDP).
Keywords: ssdp,python,asyncio,upnp,iot
Author-email: Johannes Maron <johannes@maron.family>
Requires-Python: >=3.9
Classifier: Development Status :: 5 - Production/Stable
Classifier: Environment :: Console
Classifier: Intended Audience :: Developers
Classifier: Intended Audience :: Information Technology
Classifier: License :: OSI Approved :: MIT License
Classifier: Operating System :: OS Independent
Classifier: Programming Language :: Python
Classifier: Programming Language :: Python :: 3
Classifier: Programming Language :: Python :: 3 :: Only
Classifier: Programming Language :: Python :: 3.9
Classifier: Programming Language :: Python :: 3.10
Classifier: Programming Language :: Python :: 3.11
Classifier: Programming Language :: Python :: 3.12
Classifier: Programming Language :: Python :: 3.13
Classifier: Framework :: AsyncIO
Classifier: Topic :: System :: Networking
Classifier: Topic :: Software Development :: Libraries
Classifier: Topic :: Home Automation
License-File: LICENSE
Requires-Dist: click ; extra == "cli"
Requires-Dist: Pygments ; extra == "cli"
Requires-Dist: pre-commit ; extra == "lint"
Requires-Dist: ruff ; extra == "lint"
Requires-Dist: Pygments ; extra == "pygments"
Requires-Dist: pytest ; extra == "test"
Requires-Dist: pytest-cov ; extra == "test"
Project-URL: Changelog, https://github.com/codingjoe/ssdp/releases
Project-URL: Project-URL, https://github.com/codingjoe/ssdp
Provides-Extra: cli
Provides-Extra: lint
Provides-Extra: pygments
Provides-Extra: test
